yet/__init__.py
yet/loader.py
yet/main.py
yet/structures.py
YeT-0.1.2.dist-info/LICENSE
YeT-0.1.2.dist-info/METADATA
YeT-0.1.2.dist-info/WHEEL
YeT-0.1.2.dist-info/entry_points.txt
YeT-0.1.2.dist-info/top_level.txt
YeT-0.1.2.dist-info/RECORD
