Metadata-Version: 2.1
Name: YeT
Version: 0.1.2
Summary: Elegant TeX script in YAML style
Home-page: https://github.com/BayMinimum/YeT
Author: Sangbum Kim
Author-email: bearksb1115@gmail.com
License: UNKNOWN
Project-URL: Bug Reports, https://github.com/BayMinimum/YeT/issues
Project-URL: Source, https://github.com/BayMinimum/YeT
Keywords: latex yaml
Platform: UNKNOWN
Classifier: Development Status :: 3 - Alpha
Classifier: Intended Audience :: Developers
Classifier: Intended Audience :: Education
Classifier: Intended Audience :: Science/Research
Classifier: Topic :: Text Processing :: Markup
Classifier: Topic :: Text Processing :: Markup :: LaTeX
Classifier: Topic :: Scientific/Engineering :: Mathematics
Classifier: Topic :: Scientific/Engineering :: Physics
Classifier: License :: OSI Approved :: MIT License
Classifier: Programming Language :: Python :: 3
Classifier: Programming Language :: Python :: 3.6
Classifier: Programming Language :: Python :: 3.7
Classifier: Programming Language :: Python :: 3.8
Requires-Python: >=3.6
Requires-Dist: PyYAML
